{
    "fields": [
        {
            "name": "id",
            "labels": "Id",
            "html-type": "number",
            "css-class": "",
            "options": {},
            "html-value": null,
            "validation": "",
            "is-on-index": true,
            "is-on-show": false,
            "is-on-form": false,
            "data-type": "int",
            "data-type-params": [],
            "data-value": null,
            "is-index": false,
            "is-unique": false,
            "is-primary": true,
            "comment": null,
            "is-nullable": false,
            "is-header": false,
            "is-unsigned": true,
            "is-auto-increment": true,
            "is-inline-options": false,
            "is-date": false,
            "date-format": "",
            "cast-as": "",
            "placeholder": {},
            "delimiter": "; ",
            "range": [],
            "foreign-relation": null,
            "foreign-constraint": null,
            "on-store": null,
            "on-update": null
        },
        {
            "name": "user_id",
            "labels": "User",
            "html-type": "select",
            "css-class": "",
            "options": {},
            "html-value": null,
            "validation": "required",
            "is-on-index": true,
            "is-on-show": true,
            "is-on-form": true,
            "data-type": "int",
            "data-type-params": [],
            "data-value": null,
            "is-index": true,
            "is-unique": false,
            "is-primary": false,
            "comment": null,
            "is-nullable": false,
            "is-header": false,
            "is-unsigned": true,
            "is-auto-increment": false,
            "is-inline-options": false,
            "is-date": false,
            "date-format": "",
            "cast-as": "",
            "placeholder": {},
            "delimiter": "; ",
            "range": [],
            "foreign-relation": {
                "name": "user",
                "type": "belongsTo",
                "params": [
                    "App\\Models\\User",
                    "user_id"
                ],
                "field": "name"
            },
            "foreign-constraint": null,
            "on-store": null,
            "on-update": null
        },
        {
            "name": "order_id",
            "labels": "Order",
            "html-type": "select",
            "css-class": "",
            "options": {},
            "html-value": null,
            "validation": "required",
            "is-on-index": true,
            "is-on-show": true,
            "is-on-form": true,
            "data-type": "int",
            "data-type-params": [],
            "data-value": null,
            "is-index": true,
            "is-unique": false,
            "is-primary": false,
            "comment": null,
            "is-nullable": false,
            "is-header": false,
            "is-unsigned": true,
            "is-auto-increment": false,
            "is-inline-options": false,
            "is-date": false,
            "date-format": "",
            "cast-as": "",
            "placeholder": {},
            "delimiter": "; ",
            "range": [],
            "foreign-relation": {
                "name": "order",
                "type": "belongsTo",
                "params": [
                    "App\\Models\\Order",
                    "order_id"
                ],
                "field": "package_name"
            },
            "foreign-constraint": null,
            "on-store": null,
            "on-update": null
        },
        {
            "name": "reference",
            "labels": "Reference",
            "html-type": "text",
            "css-class": "",
            "options": {},
            "html-value": null,
            "validation": "required|string|min:1|max:255",
            "is-on-index": true,
            "is-on-show": true,
            "is-on-form": true,
            "data-type": "string",
            "data-type-params": [
                255
            ],
            "data-value": null,
            "is-index": false,
            "is-unique": false,
            "is-primary": false,
            "comment": null,
            "is-nullable": false,
            "is-header": false,
            "is-unsigned": false,
            "is-auto-increment": false,
            "is-inline-options": false,
            "is-date": false,
            "date-format": "",
            "cast-as": "",
            "placeholder": {},
            "delimiter": "; ",
            "range": [],
            "foreign-relation": null,
            "foreign-constraint": null,
            "on-store": null,
            "on-update": null
        },
        {
            "name": "amount",
            "labels": "Amount",
            "html-type": "number",
            "css-class": "",
            "options": {},
            "html-value": null,
            "validation": "required|numeric|min:-1.0E+18|max:1.0E+18",
            "is-on-index": true,
            "is-on-show": true,
            "is-on-form": true,
            "data-type": "double",
            "data-type-params": [
                20,
                2
            ],
            "data-value": null,
            "is-index": false,
            "is-unique": false,
            "is-primary": false,
            "comment": null,
            "is-nullable": false,
            "is-header": false,
            "is-unsigned": false,
            "is-auto-increment": false,
            "is-inline-options": false,
            "is-date": false,
            "date-format": "",
            "cast-as": "",
            "placeholder": {},
            "delimiter": "; ",
            "range": [],
            "foreign-relation": null,
            "foreign-constraint": null,
            "on-store": null,
            "on-update": null
        },
        {
            "name": "thumb_image",
            "labels": "Thumb Image",
            "html-type": "file",
            "css-class": "",
            "options": {},
            "html-value": null,
            "validation": "nullable|file",
            "is-on-index": false,
            "is-on-show": true,
            "is-on-form": true,
            "data-type": "string",
            "data-type-params": [
                255
            ],
            "data-value": null,
            "is-index": false,
            "is-unique": false,
            "is-primary": false,
            "comment": null,
            "is-nullable": true,
            "is-header": false,
            "is-unsigned": false,
            "is-auto-increment": false,
            "is-inline-options": false,
            "is-date": false,
            "date-format": "",
            "cast-as": "",
            "placeholder": {},
            "delimiter": "; ",
            "range": [],
            "foreign-relation": null,
            "foreign-constraint": null,
            "on-store": null,
            "on-update": null
        },
        {
            "name": "created_at",
            "labels": "Created At",
            "html-type": "text",
            "css-class": "",
            "options": {},
            "html-value": null,
            "validation": "",
            "is-on-index": false,
            "is-on-show": true,
            "is-on-form": false,
            "data-type": "string",
            "data-type-params": [],
            "data-value": null,
            "is-index": false,
            "is-unique": false,
            "is-primary": false,
            "comment": null,
            "is-nullable": true,
            "is-header": false,
            "is-unsigned": false,
            "is-auto-increment": false,
            "is-inline-options": false,
            "is-date": false,
            "date-format": "j/n/Y g:i A",
            "cast-as": "",
            "placeholder": {},
            "delimiter": "; ",
            "range": [],
            "foreign-relation": null,
            "foreign-constraint": null,
            "on-store": null,
            "on-update": null
        },
        {
            "name": "updated_at",
            "labels": "Updated At",
            "html-type": "text",
            "css-class": "",
            "options": {},
            "html-value": null,
            "validation": "",
            "is-on-index": false,
            "is-on-show": true,
            "is-on-form": false,
            "data-type": "string",
            "data-type-params": [],
            "data-value": null,
            "is-index": false,
            "is-unique": false,
            "is-primary": false,
            "comment": null,
            "is-nullable": true,
            "is-header": false,
            "is-unsigned": false,
            "is-auto-increment": false,
            "is-inline-options": false,
            "is-date": false,
            "date-format": "j/n/Y g:i A",
            "cast-as": "",
            "placeholder": {},
            "delimiter": "; ",
            "range": [],
            "foreign-relation": null,
            "foreign-constraint": null,
            "on-store": null,
            "on-update": null
        }
    ],
    "relations": [],
    "indexes": [],
    "auto-manage-created-and-updated-at": true,
    "table-name": "bank_informations",
    "protection": {
        "is-model-protected": false,
        "is-controller-protected": false,
        "is-form-request-protected": false,
        "is-languages-protected": false,
        "is-form-view-protected": false,
        "is-index-view-protected": false,
        "is-create-view-protected": false,
        "is-edit-view-protected": false,
        "is-show-view-protected": false
    }
}